Examples/mitll_and2t/mitll_and2t.v
// ---------------------------------------------------------------------------
// Automatically extracted verilog file, created with TimEx v2.02.01
// Timing description and structural design for IARPA-BAA-14-03 via
// U.S. Air Force Research Laboratory contract FA8750-15-C-0203 and
// IARPA-BAA-16-03 via U.S. Army Research Office grant W911NF-17-1-0120.
// For questions about TimEx, contact CJ Fourie, coenrad@sun.ac.za
// (c) 2016-2018 Stellenbosch University
// ---------------------------------------------------------------------------
`timescale 1ps/100fs
module mitll_and2t (a, b, clk, out);

input
  a, b, clk;

output
  out;

reg
  out;

real
  delay_state3_clk_out = 8.0,
  ct_state0_clk_a = 2.3,
  ct_state0_clk_b = 3.0,
  ct_state1_clk_a = 6.5,
  ct_state1_clk_b = 2.7,
  ct_state2_clk_a = 2.0,
  ct_state2_clk_b = 2.9,
  ct_state3_b_b = 24.5,
  ct_state3_clk_a = 3.3,
  ct_state3_clk_b = 1.7;

reg
   errorsignal_a,
   errorsignal_b,
   errorsignal_clk;

integer
   outfile,
   cell_state; // internal state of the cell

initial
   begin
      errorsignal_a = 0;
      errorsignal_b = 0;
      errorsignal_clk = 0;
      cell_state = 0; // Startup state
      out = 0; // All outputs start at 0
   end

always @(posedge a or negedge a) // execute at positive and negative edges of input
   begin
      if ($time>4) // arbitrary steady-state time)
         begin
            if (errorsignal_a == 1'b1)  // A critical timing is active for this input
               begin
                  outfile = $fopen("errors.txt", "a");
                  $fdisplay(outfile, "Violation of critical timing in module %m; %0d ps.\n", $stime);
                  $fclose(outfile);
                  out <= 1'bX;  // Set all outputs to unknown
               end
            if (errorsignal_a == 0)
               begin
                  case (cell_state)
                     0: begin
                           cell_state = 1;  // Blocking statement -- immediately
                        end
                     1: begin
                        end
                     2: begin
                           cell_state = 3;  // Blocking statement -- immediately
                        end
                     3: begin
                        end
                  endcase
               end
         end
   end

always @(posedge b or negedge b) // execute at positive and negative edges of input
   begin
      if ($time>4) // arbitrary steady-state time)
         begin
            if (errorsignal_b == 1'b1)  // A critical timing is active for this input
               begin
                  outfile = $fopen("errors.txt", "a");
                  $fdisplay(outfile, "Violation of critical timing in module %m; %0d ps.\n", $stime);
                  $fclose(outfile);
                  out <= 1'bX;  // Set all outputs to unknown
               end
            if (errorsignal_b == 0)
               begin
                  case (cell_state)
                     0: begin
                           cell_state = 2;  // Blocking statement -- immediately
                        end
                     1: begin
                           cell_state = 3;  // Blocking statement -- immediately
                        end
                     2: begin
                        end
                     3: begin
                           errorsignal_b = 1;  // Critical timing on this input; assign immediately
                           errorsignal_b <= #(ct_state3_b_b) 0;  // Clear error signal after critical timing expires
                        end
                  endcase
               end
         end
   end

always @(posedge clk or negedge clk) // execute at positive and negative edges of input
   begin
      if ($time>4) // arbitrary steady-state time)
         begin
            if (errorsignal_clk == 1'b1)  // A critical timing is active for this input
               begin
                  outfile = $fopen("errors.txt", "a");
                  $fdisplay(outfile, "Violation of critical timing in module %m; %0d ps.\n", $stime);
                  $fclose(outfile);
                  out <= 1'bX;  // Set all outputs to unknown
               end
            if (errorsignal_clk == 0)
               begin
                  case (cell_state)
                     0: begin
                           errorsignal_a = 1;  // Critical timing on this input; assign immediately
                           errorsignal_a <= #(ct_state0_clk_a) 0;  // Clear error signal after critical timing expires
                           errorsignal_b = 1;  // Critical timing on this input; assign immediately
                           errorsignal_b <= #(ct_state0_clk_b) 0;  // Clear error signal after critical timing expires
                        end
                     1: begin
                           cell_state = 0;  // Blocking statement -- immediately
                           errorsignal_a = 1;  // Critical timing on this input; assign immediately
                           errorsignal_a <= #(ct_state1_clk_a) 0;  // Clear error signal after critical timing expires
                           errorsignal_b = 1;  // Critical timing on this input; assign immediately
                           errorsignal_b <= #(ct_state1_clk_b) 0;  // Clear error signal after critical timing expires
                        end
                     2: begin
                           cell_state = 0;  // Blocking statement -- immediately
                           errorsignal_a = 1;  // Critical timing on this input; assign immediately
                           errorsignal_a <= #(ct_state2_clk_a) 0;  // Clear error signal after critical timing expires
                           errorsignal_b = 1;  // Critical timing on this input; assign immediately
                           errorsignal_b <= #(ct_state2_clk_b) 0;  // Clear error signal after critical timing expires
                        end
                     3: begin
                           out <= #(delay_state3_clk_out) !out;
                           cell_state = 0;  // Blocking statement -- immediately
                           errorsignal_a = 1;  // Critical timing on this input; assign immediately
                           errorsignal_a <= #(ct_state3_clk_a) 0;  // Clear error signal after critical timing expires
                           errorsignal_b = 1;  // Critical timing on this input; assign immediately
                           errorsignal_b <= #(ct_state3_clk_b) 0;  // Clear error signal after critical timing expires
                        end
                  endcase
               end
         end
   end

endmodule

Examples/mitll_and2t/tb_mitll_and2t.v
// ---------------------------------------------------------------------------
// Verilog testbench file, created with TimEx v2.02.01
// Timing description and structural design for IARPA-BAA-14-03 via
// U.S. Air Force Research Laboratory contract FA8750-15-C-0203 and
// IARPA-BAA-16-03 via U.S. Army Research Office grant W911NF-17-1-0120.
// For questions about TimEx, contact CJ Fourie, coenrad@sun.ac.za
// (c) 2016-2018 Stellenbosch University
// ---------------------------------------------------------------------------
`include "mitll_and2t.v"
`timescale 1ps/100fs
module tb_mitll_and2t;
   reg a = 0;
   reg b = 0;
   reg clk = 0;
   initial
      begin
         $dumpfile("tb_mitll_and2topt.vcd");
         $dumpvars;
         // Now in state 0
         #20 a = !a;
         // Now in state 1
		 #10 clk = !clk;
         #10 a = !a;
         // Now in state 1
         #10 b = !b;
         // Now in state 3
         #10 a = !a;
         // Now in state 3
         #10 b = !b;
         // Now in state 3
         #10 clk = !clk;
         // Now in state 0
         #10 b = !b;
         // Now in state 2
         #10 a = !a;
         // Now in state 3
      end

   initial
      begin
         $display("\t\ttime,\ta,\tb,\tclk,\tout");
         $monitor("%d,\t%b,\t%b,\t%b,\t%b",$time,a,b,clk,out);
      end

   mitll_and2t DUT (a, b, clk, out);

   initial
      #100 $finish;
endmodule

Examples/mitll_and2t/tb_mitll_and2topt.vcd
$date
	Tue Oct 09 09:41:36 2018
$end
$version
	Icarus Verilog
$end
$timescale
	100fs
$end
$scope module tb_mitll_and2t $end
$var wire 1 ! out $end
$var reg 1 " a $end
$var reg 1 # b $end
$var reg 1 $ clk $end
$scope module DUT $end
$var wire 1 " a $end
$var wire 1 # b $end
$var wire 1 $ clk $end
$var reg 1 % errorsignal_a $end
$var reg 1 & errorsignal_b $end
$var reg 1 ' errorsignal_clk $end
$var reg 1 ! out $end
$var integer 32 ( cell_state [31:0] $end
$var real 1 ) ct_state0_clk_a $end
$var real 1 * ct_state0_clk_b $end
$var real 1 + ct_state1_clk_a $end
$var real 1 , ct_state1_clk_b $end
$var real 1 - ct_state2_clk_a $end
$var real 1 . ct_state2_clk_b $end
$var real 1 / ct_state3_b_b $end
$var real 1 0 ct_state3_clk_a $end
$var real 1 1 ct_state3_clk_b $end
$var real 1 2 delay_state3_clk_out $end
$var integer 32 3 outfile [31:0] $end
$upscope $end
$upscope $end
$enddefinitions $end
#0
$dumpvars
bx 3
r8 2
r1.7 1
r3.3 0
r24.5 /
r2.9 .
r2 -
r2.7 ,
r6.5 +
r3 *
r2.3 )
b0 (
0'
0&
0%
0$
0#
0"
0!
$end
#200
b1 (
1"
#300
1&
1%
b0 (
1$
#327
0&
#365
0%
#400
b1 (
0"
#500
b11 (
1#
#600
1"
#700
1&
0#
#800
1%
b0 (
0$
#817
0&
#833
0%
#880
1!
#900
b10 (
1#
#1000
0"
