CellLibrary/mitll_xort/LSmitll_xort.v
// ---------------------------------------------------------------------------
// Automatically extracted verilog file, created with TimEx v2.02.01
// Timing description and structural design for IARPA-BAA-14-03 via
// U.S. Air Force Research Laboratory contract FA8750-15-C-0203 and
// IARPA-BAA-16-03 via U.S. Army Research Office grant W911NF-17-1-0120.
// For questions about TimEx, contact CJ Fourie, coenrad@sun.ac.za
// (c) 2016-2018 Stellenbosch University
// ---------------------------------------------------------------------------
`timescale 1ps/100fs
module mitll_xort (a, b, clk, out);

input
  a, b, clk;

output
  out;

reg
  out;

real
  delay_state1_clk_out = 5.7,
  delay_state2_clk_out = 5.7,
  ct_state0_a_clk = 2.7,
  ct_state0_b_clk = 2.7,
  ct_state1_a_b = 8.3,
  ct_state1_a_clk = 11.6,
  ct_state1_b_b = 3.0,
  ct_state1_clk_b = 4.9,
  ct_state2_a_a = 3.0,
  ct_state2_b_a = 8.3,
  ct_state2_b_clk = 11.6,
  ct_state2_clk_a = 4.9;

reg
   errorsignal_a,
   errorsignal_b,
   errorsignal_clk;

integer
   outfile,
   cell_state; // internal state of the cell

initial
   begin
      errorsignal_a = 0;
      errorsignal_b = 0;
      errorsignal_clk = 0;
      cell_state = 0; // Startup state
      out = 0; // All outputs start at 0
   end

always @(posedge a or negedge a) // execute at positive and negative edges of input
   begin
      if ($time>4) // arbitrary steady-state time)
         begin
            if (errorsignal_a == 1'b1)  // A critical timing is active for this input
               begin
                  outfile = $fopen("errors.txt", "a");
                  $fdisplay(outfile, "Violation of critical timing in module %m; %0d ps.\n", $stime);
                  $fclose(outfile);
                  out <= 1'bX;  // Set all outputs to unknown
               end
            if (errorsignal_a == 0)
               begin
                  case (cell_state)
                     0: begin
                           cell_state = 1;  // Blocking statement -- immediately
                           errorsignal_clk = 1;  // Critical timing on this input; assign immediately
                           errorsignal_clk <= #(ct_state0_a_clk) 0;  // Clear error signal after critical timing expires
                        end
                     1: begin
                           errorsignal_b = 1;  // Critical timing on this input; assign immediately
                           errorsignal_b <= #(ct_state1_a_b) 0;  // Clear error signal after critical timing expires
                           errorsignal_clk = 1;  // Critical timing on this input; assign immediately
                           errorsignal_clk <= #(ct_state1_a_clk) 0;  // Clear error signal after critical timing expires
                        end
                     2: begin
                           cell_state = 0;  // Blocking statement -- immediately
                           errorsignal_a = 1;  // Critical timing on this input; assign immediately
                           errorsignal_a <= #(ct_state2_a_a) 0;  // Clear error signal after critical timing expires
                        end
                  endcase
               end
         end
   end

always @(posedge b or negedge b) // execute at positive and negative edges of input
   begin
      if ($time>4) // arbitrary steady-state time)
         begin
            if (errorsignal_b == 1'b1)  // A critical timing is active for this input
               begin
                  outfile = $fopen("errors.txt", "a");
                  $fdisplay(outfile, "Violation of critical timing in module %m; %0d ps.\n", $stime);
                  $fclose(outfile);
                  out <= 1'bX;  // Set all outputs to unknown
               end
            if (errorsignal_b == 0)
               begin
                  case (cell_state)
                     0: begin
                           cell_state = 2;  // Blocking statement -- immediately
                           errorsignal_clk = 1;  // Critical timing on this input; assign immediately
                           errorsignal_clk <= #(ct_state0_b_clk) 0;  // Clear error signal after critical timing expires
                        end
                     1: begin
                           cell_state = 0;  // Blocking statement -- immediately
                           errorsignal_b = 1;  // Critical timing on this input; assign immediately
                           errorsignal_b <= #(ct_state1_b_b) 0;  // Clear error signal after critical timing expires
                        end
                     2: begin
                           errorsignal_a = 1;  // Critical timing on this input; assign immediately
                           errorsignal_a <= #(ct_state2_b_a) 0;  // Clear error signal after critical timing expires
                           errorsignal_clk = 1;  // Critical timing on this input; assign immediately
                           errorsignal_clk <= #(ct_state2_b_clk) 0;  // Clear error signal after critical timing expires
                        end
                  endcase
               end
         end
   end

always @(posedge clk or negedge clk) // execute at positive and negative edges of input
   begin
      if ($time>4) // arbitrary steady-state time)
         begin
            if (errorsignal_clk == 1'b1)  // A critical timing is active for this input
               begin
                  outfile = $fopen("errors.txt", "a");
                  $fdisplay(outfile, "Violation of critical timing in module %m; %0d ps.\n", $stime);
                  $fclose(outfile);
                  out <= 1'bX;  // Set all outputs to unknown
               end
            if (errorsignal_clk == 0)
               begin
                  case (cell_state)
                     0: begin
                        end
                     1: begin
                           out <= #(delay_state1_clk_out) !out;
                           cell_state = 0;  // Blocking statement -- immediately
                           errorsignal_b = 1;  // Critical timing on this input; assign immediately
                           errorsignal_b <= #(ct_state1_clk_b) 0;  // Clear error signal after critical timing expires
                        end
                     2: begin
                           out <= #(delay_state2_clk_out) !out;
                           cell_state = 0;  // Blocking statement -- immediately
                           errorsignal_a = 1;  // Critical timing on this input; assign immediately
                           errorsignal_a <= #(ct_state2_clk_a) 0;  // Clear error signal after critical timing expires
                        end
                  endcase
               end
         end
   end

endmodule

Examples/mitll_xort/tb_mitll_xort.v
// ---------------------------------------------------------------------------
// Verilog testbench file, created with TimEx v2.02.01
// Timing description and structural design for IARPA-BAA-14-03 via
// U.S. Air Force Research Laboratory contract FA8750-15-C-0203 and
// IARPA-BAA-16-03 via U.S. Army Research Office grant W911NF-17-1-0120.
// For questions about TimEx, contact CJ Fourie, coenrad@sun.ac.za
// (c) 2016-2018 Stellenbosch University
// ---------------------------------------------------------------------------
`include "mitll_xort.v"
`timescale 1ps/100fs
module tb_mitll_xort;
   reg a = 0;
   reg b = 0;
   reg clk = 0;
   initial
      begin
         $dumpfile("tb_mitll_xort.vcd");
         $dumpvars;
         // Now in state 0
         #20 a = !a;
         // Now in state 1
         #10 a = !a;
		 #20 clk = !clk;
         // Now in state 1
         #10 b = !b;
         // Now in state 0
         #10 b = !b;
         // Now in state 2
         #10 a = !a;
         // Now in state 0
         #10 clk = !clk;
         // Now in state 0
      end

   initial
      begin
         $display("\t\ttime,\ta,\tb,\tclk,\tout");
         $monitor("%d,\t%b,\t%b,\t%b,\t%b",$time,a,b,clk,out);
      end

   mitll_xort DUT (a, b, clk, out);

   initial
      #150 $finish;
endmodule

Examples/mitll_xort/tb_mitll_xort.vcd
$date
	Tue Oct 09 09:54:00 2018
$end
$version
	Icarus Verilog
$end
$timescale
	100fs
$end
$scope module tb_mitll_xort $end
$var wire 1 ! out $end
$var reg 1 " a $end
$var reg 1 # b $end
$var reg 1 $ clk $end
$scope module DUT $end
$var wire 1 " a $end
$var wire 1 # b $end
$var wire 1 $ clk $end
$var reg 1 % errorsignal_a $end
$var reg 1 & errorsignal_b $end
$var reg 1 ' errorsignal_clk $end
$var reg 1 ! out $end
$var integer 32 ( cell_state [31:0] $end
$var real 1 ) ct_state0_a_clk $end
$var real 1 * ct_state0_b_clk $end
$var real 1 + ct_state1_a_b $end
$var real 1 , ct_state1_a_clk $end
$var real 1 - ct_state1_b_b $end
$var real 1 . ct_state1_clk_b $end
$var real 1 / ct_state2_a_a $end
$var real 1 0 ct_state2_b_a $end
$var real 1 1 ct_state2_b_clk $end
$var real 1 2 ct_state2_clk_a $end
$var real 1 3 delay_state1_clk_out $end
$var real 1 4 delay_state2_clk_out $end
$var integer 32 5 outfile [31:0] $end
$upscope $end
$upscope $end
$enddefinitions $end
#0
$dumpvars
bx 5
r5.7 4
r5.7 3
r4.9 2
r11.6 1
r8.300000000000001 0
r3 /
r4.9 .
r3 -
r11.6 ,
r8.300000000000001 +
r2.7 *
r2.7 )
b0 (
0'
0&
0%
0$
0#
0"
0!
$end
#200
1'
b1 (
1"
#227
0'
#300
1'
1&
0"
#383
0&
#416
0'
#500
1&
b0 (
1$
#549
0&
#557
1!
#600
1'
b10 (
1#
#627
0'
#700
1'
1%
0#
#783
0%
#800
1%
b0 (
1"
#816
0'
#830
0%
