CellLibrary/mitll_or2t/LSmitll_or2t.v
// ---------------------------------------------------------------------------
// Automatically extracted verilog file, created with TimEx v2.02.01
// Timing description and structural design for IARPA-BAA-14-03 via
// U.S. Air Force Research Laboratory contract FA8750-15-C-0203 and
// IARPA-BAA-16-03 via U.S. Army Research Office grant W911NF-17-1-0120.
// For questions about TimEx, contact CJ Fourie, coenrad@sun.ac.za
// (c) 2016-2018 Stellenbosch University
// ---------------------------------------------------------------------------
`timescale 1ps/100fs
module mitll_or2t (a, b, clk, out);

input
  a, b, clk;

output
  out;

reg
  out;

real
  delay_state1_clk_out = 5.0,
  ct_state0_a_clk = 0.7,
  ct_state0_b_clk = 0.7,
  ct_state1_clk_a = 0.2,
  ct_state1_clk_b = 0.2;

reg
   errorsignal_a,
   errorsignal_b,
   errorsignal_clk;

integer
   outfile,
   cell_state; // internal state of the cell

initial
   begin
      errorsignal_a = 0;
      errorsignal_b = 0;
      errorsignal_clk = 0;
      cell_state = 0; // Startup state
      out = 0; // All outputs start at 0
   end

always @(posedge a or negedge a) // execute at positive and negative edges of input
   begin
      if ($time>4) // arbitrary steady-state time)
         begin
            if (errorsignal_a == 1'b1)  // A critical timing is active for this input
               begin
                  outfile = $fopen("errors.txt", "a");
                  $fdisplay(outfile, "Violation of critical timing in module %m; %0d ps.\n", $stime);
                  $fclose(outfile);
                  out <= 1'bX;  // Set all outputs to unknown
               end
            if (errorsignal_a == 0)
               begin
                  case (cell_state)
                     0: begin
                           cell_state = 1;  // Blocking statement -- immediately
                           errorsignal_clk = 1;  // Critical timing on this input; assign immediately
                           errorsignal_clk <= #(ct_state0_a_clk) 0;  // Clear error signal after critical timing expires
                        end
                     1: begin
                        end
                  endcase
               end
         end
   end

always @(posedge b or negedge b) // execute at positive and negative edges of input
   begin
      if ($time>4) // arbitrary steady-state time)
         begin
            if (errorsignal_b == 1'b1)  // A critical timing is active for this input
               begin
                  outfile = $fopen("errors.txt", "a");
                  $fdisplay(outfile, "Violation of critical timing in module %m; %0d ps.\n", $stime);
                  $fclose(outfile);
                  out <= 1'bX;  // Set all outputs to unknown
               end
            if (errorsignal_b == 0)
               begin
                  case (cell_state)
                     0: begin
                           cell_state = 1;  // Blocking statement -- immediately
                           errorsignal_clk = 1;  // Critical timing on this input; assign immediately
                           errorsignal_clk <= #(ct_state0_b_clk) 0;  // Clear error signal after critical timing expires
                        end
                     1: begin
                        end
                  endcase
               end
         end
   end

always @(posedge clk or negedge clk) // execute at positive and negative edges of input
   begin
      if ($time>4) // arbitrary steady-state time)
         begin
            if (errorsignal_clk == 1'b1)  // A critical timing is active for this input
               begin
                  outfile = $fopen("errors.txt", "a");
                  $fdisplay(outfile, "Violation of critical timing in module %m; %0d ps.\n", $stime);
                  $fclose(outfile);
                  out <= 1'bX;  // Set all outputs to unknown
               end
            if (errorsignal_clk == 0)
               begin
                  case (cell_state)
                     0: begin
                        end
                     1: begin
                           out <= #(delay_state1_clk_out) !out;
                           cell_state = 0;  // Blocking statement -- immediately
                           errorsignal_a = 1;  // Critical timing on this input; assign immediately
                           errorsignal_a <= #(ct_state1_clk_a) 0;  // Clear error signal after critical timing expires
                           errorsignal_b = 1;  // Critical timing on this input; assign immediately
                           errorsignal_b <= #(ct_state1_clk_b) 0;  // Clear error signal after critical timing expires
                        end
                  endcase
               end
         end
   end

endmodule

Examples/mitll_or2t/tb_mitll_or2t.v
// ---------------------------------------------------------------------------
// Verilog testbench file, created with TimEx v2.02.01
// Timing description and structural design for IARPA-BAA-14-03 via
// U.S. Air Force Research Laboratory contract FA8750-15-C-0203 and
// IARPA-BAA-16-03 via U.S. Army Research Office grant W911NF-17-1-0120.
// For questions about TimEx, contact CJ Fourie, coenrad@sun.ac.za
// (c) 2016-2018 Stellenbosch University
// ---------------------------------------------------------------------------
`include "mitll_or2t.v"
`timescale 1ps/100fs
module tb_mitll_or2t;
   reg a = 0;
   reg b = 0;
   reg clk = 0;
   initial
      begin
         $dumpfile("tb_mitll_or2t.vcd");
         $dumpvars;
         // Now in state 0
         #20 a = !a;
		 #10 clk = !clk;
         // Now in state 1
         #10 a = !a;
         // Now in state 1
         #10 b = !b;
         // Now in state 1
         #10 clk = !clk;
         // Now in state 0
         #10 b = !b;
         // Now in state 1
      end

   initial
      begin
         $display("\t\ttime,\ta,\tb,\tclk,\tout");
         $monitor("%d,\t%b,\t%b,\t%b,\t%b",$time,a,b,clk,out);
      end

   mitll_or2t DUT (a, b, clk, out);

   initial
      #70 $finish;
endmodule

Examples/mitll_or2t/tb_mitll_or2t.vcd
$date
	Tue Oct 09 09:46:20 2018
$end
$version
	Icarus Verilog
$end
$timescale
	100fs
$end
$scope module tb_mitll_or2t $end
$var wire 1 ! out $end
$var reg 1 " a $end
$var reg 1 # b $end
$var reg 1 $ clk $end
$scope module DUT $end
$var wire 1 " a $end
$var wire 1 # b $end
$var wire 1 $ clk $end
$var reg 1 % errorsignal_a $end
$var reg 1 & errorsignal_b $end
$var reg 1 ' errorsignal_clk $end
$var reg 1 ! out $end
$var integer 32 ( cell_state [31:0] $end
$var real 1 ) ct_state0_a_clk $end
$var real 1 * ct_state0_b_clk $end
$var real 1 + ct_state1_clk_a $end
$var real 1 , ct_state1_clk_b $end
$var real 1 - delay_state1_clk_out $end
$var integer 32 . outfile [31:0] $end
$upscope $end
$upscope $end
$enddefinitions $end
#0
$dumpvars
bx .
r5 -
r0.2 ,
r0.2 +
r0.7 *
r0.7 )
b0 (
0'
0&
0%
0$
0#
0"
0!
$end
#200
1'
b1 (
1"
#207
0'
#300
1&
1%
b0 (
1$
#302
0&
0%
#350
1!
#400
1'
b1 (
0"
#407
0'
#500
1#
#600
1&
1%
b0 (
0$
#602
0&
0%
#650
0!
#700
0#
