CellLibrary/mitll_dfft/mitll_dfft.v
// ---------------------------------------------------------------------------
// Automatically extracted verilog file, created with TimEx v2.02.01
// Timing description and structural design for IARPA-BAA-14-03 via
// U.S. Air Force Research Laboratory contract FA8750-15-C-0203 and
// IARPA-BAA-16-03 via U.S. Army Research Office grant W911NF-17-1-0120.
// For questions about TimEx, contact CJ Fourie, coenrad@sun.ac.za
// (c) 2016-2018 Stellenbosch University
// ---------------------------------------------------------------------------
`timescale 1ps/100fs
module mitll_dfft (in, clk, out);

input
  in, clk;

output
  out;

reg
  out;

real
  delay_state1_clk_out = 6.5,
  ct_state0_clk_in = 2.2,
  ct_state1_in_in = 8.7,
  ct_state1_clk_in = 3.3;

reg
   errorsignal_in,
   errorsignal_clk;

integer
   outfile,
   cell_state; // internal state of the cell

initial
   begin
      errorsignal_in = 0;
      errorsignal_clk = 0;
      cell_state = 0; // Startup state
      out = 0; // All outputs start at 0
   end

always @(posedge in or negedge in) // execute at positive and negative edges of input
   begin
      if ($time>4) // arbitrary steady-state time)
         begin
            if (errorsignal_in == 1'b1)  // A critical timing is active for this input
               begin
                  outfile = $fopen("errors.txt", "a");
                  $fdisplay(outfile, "Violation of critical timing in module %m; %0d ps.\n", $stime);
                  $fclose(outfile);
                  out <= 1'bX;  // Set all outputs to unknown
               end
            if (errorsignal_in == 0)
               begin
                  case (cell_state)
                     0: begin
                           cell_state = 1;  // Blocking statement -- immediately
                        end
                     1: begin
                           errorsignal_in = 1;  // Critical timing on this input; assign immediately
                           errorsignal_in <= #(ct_state1_in_in) 0;  // Clear error signal after critical timing expires
                        end
                  endcase
               end
         end
   end

always @(posedge clk or negedge clk) // execute at positive and negative edges of input
   begin
      if ($time>4) // arbitrary steady-state time)
         begin
            if (errorsignal_clk == 1'b1)  // A critical timing is active for this input
               begin
                  outfile = $fopen("errors.txt", "a");
                  $fdisplay(outfile, "Violation of critical timing in module %m; %0d ps.\n", $stime);
                  $fclose(outfile);
                  out <= 1'bX;  // Set all outputs to unknown
               end
            if (errorsignal_clk == 0)
               begin
                  case (cell_state)
                     0: begin
                           errorsignal_in = 1;  // Critical timing on this input; assign immediately
                           errorsignal_in <= #(ct_state0_clk_in) 0;  // Clear error signal after critical timing expires
                        end
                     1: begin
                           out <= #(delay_state1_clk_out) !out;
                           cell_state = 0;  // Blocking statement -- immediately
                           errorsignal_in = 1;  // Critical timing on this input; assign immediately
                           errorsignal_in <= #(ct_state1_clk_in) 0;  // Clear error signal after critical timing expires
                        end
                  endcase
               end
         end
   end

endmodule

Examples/mitll_dfft/tb_mitll_dfft.v
// ---------------------------------------------------------------------------
// Verilog testbench file, created with TimEx v2.02.01
// Timing description and structural design for IARPA-BAA-14-03 via
// U.S. Air Force Research Laboratory contract FA8750-15-C-0203 and
// IARPA-BAA-16-03 via U.S. Army Research Office grant W911NF-17-1-0120.
// For questions about TimEx, contact CJ Fourie, coenrad@sun.ac.za
// (c) 2016-2018 Stellenbosch University
// ---------------------------------------------------------------------------
`include "mitll_dfft.v"
`timescale 1ps/100fs
module tb_mitll_dfft;
   reg in = 0;
   reg clk = 0;
   initial
      begin
         $dumpfile("tb_mitll_dfft.vcd");
         $dumpvars;
         // Now in state 0
         #20 in = !in;
         // Now in state 1
         #10 in = !in;
         // Now in state 1
         #10 clk = !clk;
         // Now in state 0
         #10 clk = !clk;
         // Now in state 0
      end

   initial
      begin
         $display("\t\ttime,\tin,\tclk,\tout");
         $monitor("%d,\t%b,\t%b,\t%b",$time,in,clk,out);
      end

   mitll_dfft DUT (in, clk, out);

   initial
      #60 $finish;
endmodule

Examples/mitll_dfft/tb_mitll_dfft.vcd
$date
	Tue Oct 09 09:32:06 2018
$end
$version
	Icarus Verilog
$end
$timescale
	100fs
$end
$scope module tb_mitll_dfft $end
$var wire 1 ! out $end
$var reg 1 " clk $end
$var reg 1 # in $end
$scope module DUT $end
$var wire 1 " clk $end
$var wire 1 # in $end
$var reg 1 $ errorsignal_clk $end
$var reg 1 % errorsignal_in $end
$var reg 1 ! out $end
$var integer 32 & cell_state [31:0] $end
$var real 1 ' ct_state0_clk_in $end
$var real 1 ( ct_state1_clk_in $end
$var real 1 ) ct_state1_in_in $end
$var real 1 * delay_state1_clk_out $end
$var integer 32 + outfile [31:0] $end
$upscope $end
$upscope $end
$enddefinitions $end
#0
$dumpvars
bx +
r6.5 *
r8.699999999999999 )
r3.3 (
r2.2 '
b0 &
0%
0$
0#
0"
0!
$end
#200
b1 &
1#
#300
1%
0#
#387
0%
#400
1%
b0 &
1"
#433
0%
#465
1!
#500
1%
0"
#522
0%
