CellLibrary/mitll_nott/LSmitll_nott.v
// ---------------------------------------------------------------------------
// Automatically extracted verilog file, created with TimEx v2.02.01
// Timing description and structural design for IARPA-BAA-14-03 via
// U.S. Air Force Research Laboratory contract FA8750-15-C-0203 and
// IARPA-BAA-16-03 via U.S. Army Research Office grant W911NF-17-1-0120.
// For questions about TimEx, contact CJ Fourie, coenrad@sun.ac.za
// (c) 2016-2018 Stellenbosch University
// ---------------------------------------------------------------------------
`timescale 1ps/100fs
module test_nott (in, clk, out);

input
  in, clk;

output
  out;

reg
  out;

real
  delay_state0_clk_out = 14.0,
  ct_state0_clk_in = 7.4,
  ct_state0_clk_clk = 15.9,
  ct_state1_in_clk = 10.9;

reg
   errorsignal_in,
   errorsignal_clk;

integer
   outfile,
   cell_state; // internal state of the cell

initial
   begin
      errorsignal_in = 0;
      errorsignal_clk = 0;
      cell_state = 0; // Startup state
      out = 0; // All outputs start at 0
   end

always @(posedge in or negedge in) // execute at positive and negative edges of input
   begin
      if ($time>4) // arbitrary steady-state time)
         begin
            if (errorsignal_in == 1'b1)  // A critical timing is active for this input
               begin
                  outfile = $fopen("errors.txt", "a");
                  $fdisplay(outfile, "Violation of critical timing in module %m; %0d ps.\n", $stime);
                  $fclose(outfile);
                  out <= 1'bX;  // Set all outputs to unknown
               end
            if (errorsignal_in == 0)
               begin
                  case (cell_state)
                     0: begin
                           cell_state = 1;  // Blocking statement -- immediately
                        end
                     1: begin
                           errorsignal_clk = 1;  // Critical timing on this input; assign immediately
                           errorsignal_clk <= #(ct_state1_in_clk) 0;  // Clear error signal after critical timing expires
                        end
                  endcase
               end
         end
   end

always @(posedge clk or negedge clk) // execute at positive and negative edges of input
   begin
      if ($time>4) // arbitrary steady-state time)
         begin
            if (errorsignal_clk == 1'b1)  // A critical timing is active for this input
               begin
                  outfile = $fopen("errors.txt", "a");
                  $fdisplay(outfile, "Violation of critical timing in module %m; %0d ps.\n", $stime);
                  $fclose(outfile);
                  out <= 1'bX;  // Set all outputs to unknown
               end
            if (errorsignal_clk == 0)
               begin
                  case (cell_state)
                     0: begin
                           out <= #(delay_state0_clk_out) !out;
                           errorsignal_in = 1;  // Critical timing on this input; assign immediately
                           errorsignal_in <= #(ct_state0_clk_in) 0;  // Clear error signal after critical timing expires
                           errorsignal_clk = 1;  // Critical timing on this input; assign immediately
                           errorsignal_clk <= #(ct_state0_clk_clk) 0;  // Clear error signal after critical timing expires
                        end
                     1: begin
                           cell_state = 0;  // Blocking statement -- immediately
                        end
                  endcase
               end
         end
   end

endmodule

Examples/mitll_nott/tb_mitll_nott.v
// ---------------------------------------------------------------------------
// Verilog testbench file, created with TimEx v2.02.01
// Timing description and structural design for IARPA-BAA-14-03 via
// U.S. Air Force Research Laboratory contract FA8750-15-C-0203 and
// IARPA-BAA-16-03 via U.S. Army Research Office grant W911NF-17-1-0120.
// For questions about TimEx, contact CJ Fourie, coenrad@sun.ac.za
// (c) 2016-2018 Stellenbosch University
// ---------------------------------------------------------------------------
`include "mitll_nott.v"
`timescale 1ps/100fs
module tb_test_nott;
   reg in = 0;
   reg clk = 0;
   initial
      begin
         $dumpfile("tb_test_nott.vcd");
         $dumpvars;
         // Now in state 0
         #20 in = !in;
         // Now in state 1
         #10 in = !in;
         // Now in state 1
         #20 clk = !clk;
         // Now in state 0
         #20 clk = !clk;
         // Now in state 0
		 #20 clk = !clk;
      end

   initial
      begin
         $display("\t\ttime,\tin,\tclk,\tout");
         $monitor("%d,\t%b,\t%b,\t%b",$time,in,clk,out);
      end

   test_nott DUT (in, clk, out);

   initial
      #200 $finish;
endmodule

Examples/mitll_nott/tb_test_nott.vcd
$date
	Tue Oct 09 09:37:59 2018
$end
$version
	Icarus Verilog
$end
$timescale
	100fs
$end
$scope module tb_test_nott $end
$var wire 1 ! out $end
$var reg 1 " clk $end
$var reg 1 # in $end
$scope module DUT $end
$var wire 1 " clk $end
$var wire 1 # in $end
$var reg 1 $ errorsignal_clk $end
$var reg 1 % errorsignal_in $end
$var reg 1 ! out $end
$var integer 32 & cell_state [31:0] $end
$var real 1 ' ct_state0_clk_clk $end
$var real 1 ( ct_state0_clk_in $end
$var real 1 ) ct_state1_in_clk $end
$var real 1 * delay_state0_clk_out $end
$var integer 32 + outfile [31:0] $end
$upscope $end
$upscope $end
$enddefinitions $end
#0
$dumpvars
bx +
r14 *
r10.9 )
r7.4 (
r15.9 '
b0 &
0%
0$
0#
0"
0!
$end
#200
b1 &
1#
#300
1$
0#
#409
0$
#500
b0 &
1"
#700
1$
1%
0"
#774
0%
#840
1!
#859
0$
#900
1$
1%
1"
#974
0%
#1040
0!
