CellLibrary/mitll_merget/LSmitll_merget.v
// ---------------------------------------------------------------------------
// Automatically extracted verilog file, created with TimEx v2.02.01
// Timing description and structural design for IARPA-BAA-14-03 via
// U.S. Air Force Research Laboratory contract FA8750-15-C-0203 and
// IARPA-BAA-16-03 via U.S. Army Research Office grant W911NF-17-1-0120.
// For questions about TimEx, contact CJ Fourie, coenrad@sun.ac.za
// (c) 2016-2018 Stellenbosch University
// ---------------------------------------------------------------------------
`timescale 1ps/100fs
module mitll_merget (a, b, out);

input
  a, b;

output
  out;

reg
  out;

real
  delay_state0_a_out = 4.0,
  delay_state0_b_out = 4.0,
  ct_state0_a_a = 5.1,
  ct_state0_a_b = 1.2,
  ct_state0_b_a = 1.2,
  ct_state0_b_b = 5.1;

reg
   errorsignal_a,
   errorsignal_b;

integer
   outfile,
   cell_state; // internal state of the cell

initial
   begin
      errorsignal_a = 0;
      errorsignal_b = 0;
      cell_state = 0; // Startup state
      out = 0; // All outputs start at 0
   end

always @(posedge a or negedge a) // execute at positive and negative edges of input
   begin
      if ($time>4) // arbitrary steady-state time)
         begin
            if (errorsignal_a == 1'b1)  // A critical timing is active for this input
               begin
                  outfile = $fopen("errors.txt", "a");
                  $fdisplay(outfile, "Violation of critical timing in module %m; %0d ps.\n", $stime);
                  $fclose(outfile);
                  out <= 1'bX;  // Set all outputs to unknown
               end
            if (errorsignal_a == 0)
               begin
                  case (cell_state)
                     0: begin
                           out <= #(delay_state0_a_out) !out;
                           errorsignal_a = 1;  // Critical timing on this input; assign immediately
                           errorsignal_a <= #(ct_state0_a_a) 0;  // Clear error signal after critical timing expires
                           errorsignal_b = 1;  // Critical timing on this input; assign immediately
                           errorsignal_b <= #(ct_state0_a_b) 0;  // Clear error signal after critical timing expires
                        end
                  endcase
               end
         end
   end

always @(posedge b or negedge b) // execute at positive and negative edges of input
   begin
      if ($time>4) // arbitrary steady-state time)
         begin
            if (errorsignal_b == 1'b1)  // A critical timing is active for this input
               begin
                  outfile = $fopen("errors.txt", "a");
                  $fdisplay(outfile, "Violation of critical timing in module %m; %0d ps.\n", $stime);
                  $fclose(outfile);
                  out <= 1'bX;  // Set all outputs to unknown
               end
            if (errorsignal_b == 0)
               begin
                  case (cell_state)
                     0: begin
                           out <= #(delay_state0_b_out) !out;
                           errorsignal_a = 1;  // Critical timing on this input; assign immediately
                           errorsignal_a <= #(ct_state0_b_a) 0;  // Clear error signal after critical timing expires
                           errorsignal_b = 1;  // Critical timing on this input; assign immediately
                           errorsignal_b <= #(ct_state0_b_b) 0;  // Clear error signal after critical timing expires
                        end
                  endcase
               end
         end
   end

endmodule

Examples/mitll_merget/tb_mitll_merget.v
// ---------------------------------------------------------------------------
// Verilog testbench file, created with TimEx v2.02.01
// Timing description and structural design for IARPA-BAA-14-03 via
// U.S. Air Force Research Laboratory contract FA8750-15-C-0203 and
// IARPA-BAA-16-03 via U.S. Army Research Office grant W911NF-17-1-0120.
// For questions about TimEx, contact CJ Fourie, coenrad@sun.ac.za
// (c) 2016-2018 Stellenbosch University
// ---------------------------------------------------------------------------
`include "mitll_merget.v"
`timescale 1ps/100fs
module tb_mitll_merget;
   reg a = 0;
   reg b = 0;
   initial
      begin
         $dumpfile("tb_mitll_merget.vcd");
         $dumpvars;
         // Now in state 0
         #20 a = !a;
         // Now in state 0
         #10 b = !b;
         // Now in state 0
      end

   initial
      begin
         $display("\t\ttime,\ta,\tb,\tout");
         $monitor("%d,\t%b,\t%b,\t%b",$time,a,b,out);
      end

   mitll_merget DUT (a, b, out);

   initial
      #40 $finish;
endmodule

Examples/mitll_merget/tb_mitll_merget.vcd
$date
	Tue Oct 09 09:30:38 2018
$end
$version
	Icarus Verilog
$end
$timescale
	100fs
$end
$scope module tb_mitll_merget $end
$var wire 1 ! out $end
$var reg 1 " a $end
$var reg 1 # b $end
$scope module DUT $end
$var wire 1 " a $end
$var wire 1 # b $end
$var reg 1 $ errorsignal_a $end
$var reg 1 % errorsignal_b $end
$var reg 1 ! out $end
$var integer 32 & cell_state [31:0] $end
$var real 1 ' ct_state0_a_a $end
$var real 1 ( ct_state0_a_b $end
$var real 1 ) ct_state0_b_a $end
$var real 1 * ct_state0_b_b $end
$var real 1 + delay_state0_a_out $end
$var real 1 , delay_state0_b_out $end
$var integer 32 - outfile [31:0] $end
$upscope $end
$upscope $end
$enddefinitions $end
#0
$dumpvars
bx -
r4 ,
r4 +
r5.1 *
r1.2 )
r1.2 (
r5.1 '
b0 &
0%
0$
0#
0"
0!
$end
#200
1%
1$
1"
#212
0%
#240
x!
b10000000000000000000000000000011 -
0"
#251
0$
#340
1%
1$
1#
#352
0$
#391
0%
